{"assets":{"FA4EA8C2B2453A2ABD2741C8C944964C":{"type":"texture","index":3,"url":{"native":"assets\/8554EC50-5A3A-43A3-8DFB-291473318106.pdf"},"width":941,"height":68},"4EDDA9365989C60F31824B3B04839638":{"type":"texture","index":4,"url":{"native":"assets\/8554EC50-5A3A-43A3-8DFB-291473318106.pdf"},"width":879,"height":88},"4C59AFC708246E52175AA6414ACEAEF1":{"type":"texture","index":8,"url":{"native":"assets\/8554EC50-5A3A-43A3-8DFB-291473318106.pdf"},"width":1024,"height":768},"80E549313E6B8EF3E7F6E6F923B49386":{"type":"texture","index":7,"url":{"native":"assets\/8554EC50-5A3A-43A3-8DFB-291473318106.pdf"},"width":1024,"height":768},"9251636AE7EC24F2536617C9E7909BA3":{"type":"texture","index":0,"url":{"native":"assets\/8554EC50-5A3A-43A3-8DFB-291473318106.pdf"},"width":1024,"height":768},"ED29C62767A41465D6783C5C27326D53":{"type":"texture","index":1,"url":{"native":"assets\/8554EC50-5A3A-43A3-8DFB-291473318106.pdf"},"width":972,"height":101},"031D85F0AC0685B6A950E6766B703A20":{"type":"texture","index":6,"url":{"native":"assets\/8554EC50-5A3A-43A3-8DFB-291473318106.pdf"},"width":941,"height":68},"D2CF0D74CEA9355D4191ED6ED1D34A11":{"type":"texture","index":2,"url":{"native":"assets\/8554EC50-5A3A-43A3-8DFB-291473318106.pdf"},"width":84,"height":58},"EFC639BC6D2B9DA8890427392A014891":{"type":"texture","index":5,"url":{"native":"assets\/8554EC50-5A3A-43A3-8DFB-291473318106.pdf"},"width":1045,"height":303}},"events":[{"effects":[{"beginTime":0,"baseLayer":{"animations":[],"initialState":{"affineTransform":[1,0,0,1,0,0],"masksToBounds":false,"rotation":0,"scale":1,"position":{"pointX":508.59586715698242,"pointY":393.79514956474304},"width":941,"sublayerTransform":[1,0,0,0,0,1,0,0,0,0,1,0,0,0,0,1],"contentsRect":{"y":0,"x":0,"width":1,"height":1},"opacity":1,"edgeAntialiasingMask":251658240,"height":68,"hidden":false,"anchorPoint":{"pointX":0.5,"pointY":0.5}},"objectID":"87B8599C-80D5-4128-A775-69BBD845A03A","layers":[{"animations":[],"initialState":{"affineTransform":[1,0,0,1,0,0],"masksToBounds":false,"rotation":0,"scale":1,"position":{"pointX":473.90413284301758,"pointY":24.204850435256958},"width":941,"sublayerTransform":[1,0,0,0,0,1,0,0,0,0,1,-0.00049229876906403734,0,0,0,1],"contentsRect":{"y":0,"x":0,"width":1,"height":1},"opacity":1,"edgeAntialiasingMask":251658240,"height":68,"hidden":false,"anchorPoint":{"pointX":0.50361756943997615,"pointY":0.35595368287142587}},"layers":[{"animations":[{"additive":false,"timeOffset":0,"beginTime":1e-100,"repeatCount":0,"fillMode":"both","duration":1,"autoreverses":false,"animations":[{"repeatCount":0,"removedOnCompletion":true,"from":{"scalar":0},"timingFunction":"EaseInEaseOut","additive":false,"timeOffset":0,"autoreverses":false,"property":"opacity","fillMode":"both","duration":1,"beginTime":0,"to":{"scalar":1}},{"additive":false,"timeOffset":0,"beginTime":0,"from":{"scalar":false},"repeatCount":0,"fillMode":"forwards","duration":1,"autoreverses":false,"property":"hidden","to":{"scalar":false},"removedOnCompletion":true}],"removedOnCompletion":false}],"layers":[],"texturedRectangle":{"singleTextureOpacity":1,"textXHeight":0.23117647058823529,"textBaseline":0.88081963973886823,"isBackgroundTexture":true,"isVerticalText":false,"textColor":[0,0,0,1],"textureType":6},"initialState":{"affineTransform":[1,0,0,1,0,0],"masksToBounds":false,"rotation":0,"scale":1,"position":{"pointX":475.40413284301758,"pointY":43.204850435256958},"width":941,"sublayerTransform":[1,0,0,0,0,1,0,0,0,0,1,0,0,0,0,1],"contentsRect":{"y":0,"x":0,"width":1,"height":1},"opacity":1,"edgeAntialiasingMask":0,"height":68,"hidden":true,"anchorPoint":{"pointX":0.5,"pointY":0.5}},"texture":"031D85F0AC0685B6A950E6766B703A20"}]}]},"effects":[],"duration":1,"type":"buildIn","attributes":{"direction":11},"name":"apple:wipe","objectID":"87B8599C-80D5-4128-A775-69BBD845A03A"}],"automaticPlay":false,"hyperlinks":[],"accessibility":[{"text":"4","targetRectangle":{"y":261.71868896484375,"x":418.4985179901123,"width":16.6845703125,"height":36}},{"text":"3","targetRectangle":{"y":261.71868896484375,"x":567.15626335144043,"width":16.6845703125,"height":36}},{"text":"4","targetRectangle":{"y":261.71868885343139,"x":848.74531364440918,"width":16.6845703125,"height":36}},{"text":"Clases","targetRectangle":{"y":620.72070384025574,"x":5.3019928932189941,"width":79.456000000000003,"height":31}},{"text":"pasted-image.pdf","targetRectangle":{"y":528.1990966796875,"x":868.9886372089386,"width":23.701805114746094,"height":198.83560180664062}},{"text":"3","targetRectangle":{"y":261.71868896484375,"x":699.3549633026123,"width":16.6845703125,"height":36}},{"text":"2","targetRectangle":{"y":261.71868896484375,"x":107.23579216003418,"width":16.6845703125,"height":36}},{"text":"￼","targetRectangle":{"y":719.260009765625,"x":967.53321838378906,"width":36.7060546875,"height":36.92041015625}},{"text":"Screenshot 2019-01-11 01.07.24.png","targetRectangle":{"y":301.1778450012207,"x":75.729095458984375,"width":868.82037353515625,"height":30.681858062744141}},{"text":"1.5 Distribuciones de frecuencias (ejemplo 1)","targetRectangle":{"y":39.050423622131348,"x":29.337646484375,"width":965.32470703125,"height":54}},{"text":"1.2 Descripción de datos: frecuencia de clase","targetRectangle":{"y":93.050423622131348,"x":25.54736328125,"width":972.9052734375,"height":54}},{"text":"4","targetRectangle":{"y":261.71868896484375,"x":241.96590995788574,"width":16.6845703125,"height":36}},{"text":"Frecuencia ","targetRectangle":{"y":605.22070372104645,"x":892.4260086193085,"width":136.83799999999997,"height":31}},{"text":"absoluta","targetRectangle":{"y":636.22070372104645,"x":907.37600861930844,"width":99.710000000000036,"height":31}},{"text":"pasted-image.pdf","targetRectangle":{"y":530.04998779296875,"x":91.696133852005005,"width":23.701805114746094,"height":195.13386535644531}},{"text":"La variable de estudio es el número de refrescos de cola que un joven bebe al día. Por lo tanto, los posibles valores de esta variable son:","targetRectangle":{"y":179.26431155204773,"x":42.095867156982422,"width":948.14822753906208,"height":72.000457763671875}}],"baseLayer":{"animations":[],"initialState":{"affineTransform":[1,0,0,1,0,0],"masksToBounds":false,"rotation":0,"scale":1,"position":{"pointX":512,"pointY":384},"width":1024,"sublayerTransform":[1,0,0,0,0,1,0,0,0,0,1,0,0,0,0,1],"contentsRect":{"y":0,"x":0,"width":1,"height":1},"opacity":1,"edgeAntialiasingMask":251658240,"height":768,"hidden":false,"anchorPoint":{"pointX":0.5,"pointY":0.5}},"layers":[{"animations":[],"initialState":{"affineTransform":[1,0,0,1,0,0],"masksToBounds":false,"rotation":0,"scale":1,"position":{"pointX":512,"pointY":384},"width":1024,"sublayerTransform":[1,0,0,0,0,1,0,0,0,0,1,0,0,0,0,1],"contentsRect":{"y":0,"x":0,"width":1,"height":1},"opacity":1,"edgeAntialiasingMask":251658240,"height":768,"hidden":false,"anchorPoint":{"pointX":0.5,"pointY":0.5}},"layers":[{"animations":[],"initialState":{"affineTransform":[1,0,0,1,0,0],"masksToBounds":false,"rotation":0,"scale":1,"position":{"pointX":512,"pointY":384},"width":1024,"sublayerTransform":[1,0,0,0,0,1,0,0,0,0,1,0,0,0,0,1],"contentsRect":{"y":0,"x":0,"width":1,"height":1},"opacity":1,"edgeAntialiasingMask":251658240,"height":768,"hidden":false,"anchorPoint":{"pointX":0.5,"pointY":0.5}},"layers":[{"animations":[],"layers":[],"texturedRectangle":{"isBackgroundTexture":true,"singleTextureOpacity":1,"textureType":1,"textBaseline":0,"textXHeight":0,"isVerticalText":false},"initialState":{"affineTransform":[1,0,0,1,0,0],"masksToBounds":false,"rotation":0,"scale":1,"position":{"pointX":512,"pointY":384},"width":1024,"sublayerTransform":[1,0,0,0,0,1,0,0,0,0,1,0,0,0,0,1],"contentsRect":{"y":0,"x":0,"width":1,"height":1},"opacity":1,"edgeAntialiasingMask":0,"height":768,"hidden":false,"anchorPoint":{"pointX":0.5,"pointY":0.5}},"texture":"9251636AE7EC24F2536617C9E7909BA3"}]}]},{"animations":[],"initialState":{"affineTransform":[1,0,0,1,0,0],"masksToBounds":false,"rotation":0,"scale":1,"position":{"pointX":512,"pointY":384},"width":1024,"sublayerTransform":[1,0,0,0,0,1,0,0,0,0,1,0,0,0,0,1],"contentsRect":{"y":0,"x":0,"width":1,"height":1},"opacity":1,"edgeAntialiasingMask":251658240,"height":768,"hidden":false,"anchorPoint":{"pointX":0.5,"pointY":0.5}},"layers":[{"animations":[],"initialState":{"affineTransform":[1,0,0,1,0,0],"masksToBounds":false,"rotation":0,"scale":1,"position":{"pointX":507.46453857421875,"pointY":58.550423622131348},"width":972,"sublayerTransform":[1,0,0,0,0,1,0,0,0,0,1,0,0,0,0,1],"contentsRect":{"y":0,"x":0,"width":1,"height":1},"opacity":1,"edgeAntialiasingMask":251658240,"height":101,"hidden":false,"anchorPoint":{"pointX":0.5,"pointY":0.5}},"layers":[{"animations":[],"layers":[],"texturedRectangle":{"singleTextureOpacity":1,"textXHeight":0.23713064665841585,"textBaseline":0.87823071810278563,"isBackgroundTexture":true,"isVerticalText":false,"textColor":[0.016150906682014465,0.20410424470901489,1,1],"textureType":6},"initialState":{"affineTransform":[1,0,0,1,0,0],"masksToBounds":false,"rotation":0,"scale":1,"position":{"pointX":491.53546142578125,"pointY":90.449576377868652},"width":972,"sublayerTransform":[1,0,0,0,0,1,0,0,0,0,1,0,0,0,0,1],"contentsRect":{"y":0,"x":0,"width":1,"height":1},"opacity":1,"edgeAntialiasingMask":0,"height":101,"hidden":false,"anchorPoint":{"pointX":0.5,"pointY":0.5}},"texture":"ED29C62767A41465D6783C5C27326D53"}]}]},{"animations":[],"initialState":{"affineTransform":[1,0,0,1,0,0],"masksToBounds":false,"rotation":0,"scale":1,"position":{"pointX":512,"pointY":384},"width":1024,"sublayerTransform":[1,0,0,0,0,1,0,0,0,0,1,0,0,0,0,1],"contentsRect":{"y":0,"x":0,"width":1,"height":1},"opacity":1,"edgeAntialiasingMask":251658240,"height":768,"hidden":false,"anchorPoint":{"pointX":0.5,"pointY":0.5}},"layers":[{"animations":[],"initialState":{"affineTransform":[1,0,0,1,0,0],"masksToBounds":false,"rotation":0,"scale":1,"position":{"pointX":987.28802490234375,"pointY":739.260009765625},"width":84,"sublayerTransform":[1,0,0,0,0,1,0,0,0,0,1,0,0,0,0,1],"contentsRect":{"y":0,"x":0,"width":1,"height":1},"opacity":1,"edgeAntialiasingMask":251658240,"height":58,"hidden":false,"anchorPoint":{"pointX":0.5,"pointY":0.5}},"layers":[{"animations":[],"layers":[],"texturedRectangle":{"singleTextureOpacity":1,"textXHeight":0,"shapePath":{"lineWidth":1,"flatness":0.59999999999999998,"lineCapStyle":0,"elements":[{"type":"MoveToPoint","points":[[3.78802490234375,3.760009765625]]},{"type":"AddLine","points":[[79.984468936920166,3.760009765625]]},{"type":"AddLine","points":[[79.984468936920166,53.680419683456421]]},{"type":"AddLine","points":[[3.78802490234375,53.680419683456421]]},{"type":"CloseSubpath"},{"type":"MoveToPoint","points":[[3.78802490234375,3.760009765625]]}],"windingRule":0,"lineJoinStyle":0,"miterLimit":10},"isBackgroundTexture":true,"textBaseline":0,"isVerticalText":false,"textureType":5},"initialState":{"affineTransform":[1,0,0,1,0,0],"masksToBounds":false,"rotation":0,"scale":1,"position":{"pointX":40.71197509765625,"pointY":27.739990234375},"width":84,"sublayerTransform":[1,0,0,0,0,1,0,0,0,0,1,0,0,0,0,1],"contentsRect":{"y":0,"x":0,"width":1,"height":1},"opacity":1,"edgeAntialiasingMask":0,"height":58,"hidden":false,"anchorPoint":{"pointX":0.5,"pointY":0.5}},"texture":"D2CF0D74CEA9355D4191ED6ED1D34A11"}]}]},{"animations":[],"initialState":{"affineTransform":[1,0,0,1,0,0],"masksToBounds":false,"rotation":0,"scale":1,"position":{"pointX":512,"pointY":384},"width":1024,"sublayerTransform":[1,0,0,0,0,1,0,0,0,0,1,0,0,0,0,1],"contentsRect":{"y":0,"x":0,"width":1,"height":1},"opacity":1,"edgeAntialiasingMask":251658240,"height":768,"hidden":false,"anchorPoint":{"pointX":0.5,"pointY":0.5}},"layers":[{"animations":[],"initialState":{"affineTransform":[1,0,0,1,0,0],"masksToBounds":false,"rotation":0,"scale":1,"position":{"pointX":508.59586715698242,"pointY":209.26431155204773},"width":941,"sublayerTransform":[1,0,0,0,0,1,0,0,0,0,1,0,0,0,0,1],"contentsRect":{"y":0,"x":0,"width":1,"height":1},"opacity":1,"edgeAntialiasingMask":251658240,"height":68,"hidden":false,"anchorPoint":{"pointX":0.5,"pointY":0.5}},"layers":[{"animations":[],"layers":[],"texturedRectangle":{"singleTextureOpacity":1,"textXHeight":0.23117647058823529,"textBaseline":0.8730131983757019,"isBackgroundTexture":true,"isVerticalText":false,"textColor":[0,0,0,1],"textureType":6},"initialState":{"affineTransform":[1,0,0,1,0,0],"masksToBounds":false,"rotation":0,"scale":1,"position":{"pointX":475.40413284301758,"pointY":43.735688447952271},"width":941,"sublayerTransform":[1,0,0,0,0,1,0,0,0,0,1,0,0,0,0,1],"contentsRect":{"y":0,"x":0,"width":1,"height":1},"opacity":1,"edgeAntialiasingMask":0,"height":68,"hidden":false,"anchorPoint":{"pointX":0.5,"pointY":0.5}},"texture":"FA4EA8C2B2453A2ABD2741C8C944964C"}]}]},{"animations":[],"initialState":{"affineTransform":[1,0,0,1,0,0],"masksToBounds":false,"rotation":0,"scale":1,"position":{"pointX":512,"pointY":384},"width":1024,"sublayerTransform":[1,0,0,0,0,1,0,0,0,0,1,0,0,0,0,1],"contentsRect":{"y":0,"x":0,"width":1,"height":1},"opacity":1,"edgeAntialiasingMask":251658240,"height":768,"hidden":false,"anchorPoint":{"pointX":0.5,"pointY":0.5}},"layers":[{"animations":[],"initialState":{"affineTransform":[1,0,0,1,0,0],"masksToBounds":false,"rotation":0,"scale":1,"position":{"pointX":515.22909545898438,"pointY":301.71868896484375},"width":879,"sublayerTransform":[1,0,0,0,0,1,0,0,0,0,1,0,0,0,0,1],"contentsRect":{"y":0,"x":0,"width":1,"height":1},"opacity":1,"edgeAntialiasingMask":251658240,"height":88,"hidden":false,"anchorPoint":{"pointX":0.5,"pointY":0.5}},"layers":[{"animations":[],"layers":[],"texturedRectangle":{"isBackgroundTexture":true,"singleTextureOpacity":1,"textureType":5,"textBaseline":0,"textXHeight":0,"isVerticalText":false},"initialState":{"affineTransform":[1,0,0,1,0,0],"masksToBounds":false,"rotation":0,"scale":1,"position":{"pointX":436.77090454101562,"pointY":40.28131103515625},"width":879,"sublayerTransform":[1,0,0,0,0,1,0,0,0,0,1,0,0,0,0,1],"contentsRect":{"y":0,"x":0,"width":1,"height":1},"opacity":1,"edgeAntialiasingMask":0,"height":88,"hidden":false,"anchorPoint":{"pointX":0.5,"pointY":0.5}},"texture":"4EDDA9365989C60F31824B3B04839638"}]}]},{"animations":[],"initialState":{"affineTransform":[1,0,0,1,0,0],"masksToBounds":false,"rotation":0,"scale":1,"position":{"pointX":512,"pointY":384},"width":1024,"sublayerTransform":[1,0,0,0,0,1,0,0,0,0,1,0,0,0,0,1],"contentsRect":{"y":0,"x":0,"width":1,"height":1},"opacity":1,"edgeAntialiasingMask":251658240,"height":768,"hidden":false,"anchorPoint":{"pointX":0.5,"pointY":0.5}},"layers":[{"animations":[],"initialState":{"affineTransform":[1,0,0,1,0,0],"masksToBounds":false,"rotation":0,"scale":1,"position":{"pointX":523.3019917011261,"pointY":608.09909057617188},"width":1045,"sublayerTransform":[1,0,0,0,0,1,0,0,0,0,1,0,0,0,0,1],"contentsRect":{"y":0,"x":0,"width":1,"height":1},"opacity":1,"edgeAntialiasingMask":251658240,"height":303,"hidden":false,"anchorPoint":{"pointX":0.5,"pointY":0.5}},"objectID":"15131158-FFE4-47F7-8329-D4736EE47073","layers":[{"animations":[],"layers":[],"texturedRectangle":{"isBackgroundTexture":true,"singleTextureOpacity":1,"textureType":5,"textBaseline":0,"textXHeight":0,"isVerticalText":false},"initialState":{"affineTransform":[1,0,0,1,0,0],"masksToBounds":false,"rotation":0,"scale":1,"position":{"pointX":519.6980082988739,"pointY":150.90090942382812},"width":1045,"sublayerTransform":[1,0,0,0,0,1,0,0,0,0,1,0,0,0,0,1],"contentsRect":{"y":0,"x":0,"width":1,"height":1},"opacity":1,"edgeAntialiasingMask":0,"height":303,"hidden":true,"anchorPoint":{"pointX":0.5,"pointY":0.5}},"texture":"EFC639BC6D2B9DA8890427392A014891"}]}]},{"animations":[],"initialState":{"affineTransform":[1,0,0,1,0,0],"masksToBounds":false,"rotation":0,"scale":1,"position":{"pointX":512,"pointY":384},"width":1024,"sublayerTransform":[1,0,0,0,0,1,0,0,0,0,1,0,0,0,0,1],"contentsRect":{"y":0,"x":0,"width":1,"height":1},"opacity":1,"edgeAntialiasingMask":251658240,"height":768,"hidden":false,"anchorPoint":{"pointX":0.5,"pointY":0.5}},"layers":[{"animations":[],"initialState":{"affineTransform":[1,0,0,1,0,0],"masksToBounds":false,"rotation":0,"scale":1,"position":{"pointX":508.59586715698242,"pointY":393.79514956474304},"width":941,"sublayerTransform":[1,0,0,0,0,1,0,0,0,0,1,0,0,0,0,1],"contentsRect":{"y":0,"x":0,"width":1,"height":1},"opacity":1,"edgeAntialiasingMask":251658240,"height":68,"hidden":false,"anchorPoint":{"pointX":0.5,"pointY":0.5}},"objectID":"87B8599C-80D5-4128-A775-69BBD845A03A","layers":[{"animations":[],"layers":[],"texturedRectangle":{"singleTextureOpacity":1,"textXHeight":0.23117647058823529,"textBaseline":0.88081963973886823,"isBackgroundTexture":true,"isVerticalText":false,"textColor":[0,0,0,1],"textureType":6},"initialState":{"affineTransform":[1,0,0,1,0,0],"masksToBounds":false,"rotation":0,"scale":1,"position":{"pointX":475.40413284301758,"pointY":43.204850435256958},"width":941,"sublayerTransform":[1,0,0,0,0,1,0,0,0,0,1,0,0,0,0,1],"contentsRect":{"y":0,"x":0,"width":1,"height":1},"opacity":1,"edgeAntialiasingMask":0,"height":68,"hidden":true,"anchorPoint":{"pointX":0.5,"pointY":0.5}},"texture":"031D85F0AC0685B6A950E6766B703A20"}]}]}]}},{"effects":[{"beginTime":0,"baseLayer":{"animations":[],"initialState":{"affineTransform":[1,0,0,1,0,0],"masksToBounds":false,"rotation":0,"scale":1,"position":{"pointX":523.3019917011261,"pointY":608.09909057617188},"width":1045,"sublayerTransform":[1,0,0,0,0,1,0,0,0,0,1,0,0,0,0,1],"contentsRect":{"y":0,"x":0,"width":1,"height":1},"opacity":1,"edgeAntialiasingMask":251658240,"height":303,"hidden":false,"anchorPoint":{"pointX":0.5,"pointY":0.5}},"objectID":"15131158-FFE4-47F7-8329-D4736EE47073","layers":[{"animations":[],"initialState":{"affineTransform":[1,0,0,1,0,0],"masksToBounds":false,"rotation":0,"scale":1,"position":{"pointX":511.1980082988739,"pointY":-72.599090576171875},"width":1045,"sublayerTransform":[1,0,0,0,0,1,0,0,0,0,1,-0.00049229876906403734,0,0,0,1],"contentsRect":{"y":0,"x":0,"width":1,"height":1},"opacity":1,"edgeAntialiasingMask":251658240,"height":303,"hidden":false,"anchorPoint":{"pointX":0.48918469693672145,"pointY":-0.23960095899726691}},"layers":[{"animations":[{"additive":false,"timeOffset":0,"beginTime":1e-100,"repeatCount":0,"fillMode":"both","duration":0.5,"autoreverses":false,"animations":[{"repeatCount":0,"removedOnCompletion":true,"from":{"scalar":0},"timingFunction":"EaseInEaseOut","additive":false,"timeOffset":0,"autoreverses":false,"property":"opacity","fillMode":"both","duration":0.5,"beginTime":0,"to":{"scalar":1}},{"additive":false,"timeOffset":0,"beginTime":0,"from":{"scalar":false},"repeatCount":0,"fillMode":"forwards","duration":0.5,"autoreverses":false,"property":"hidden","to":{"scalar":false},"removedOnCompletion":true}],"removedOnCompletion":false}],"layers":[],"texturedRectangle":{"isBackgroundTexture":true,"singleTextureOpacity":1,"textureType":5,"textBaseline":0,"textXHeight":0,"isVerticalText":false},"initialState":{"affineTransform":[1,0,0,1,0,0],"masksToBounds":false,"rotation":0,"scale":1,"position":{"pointX":519.6980082988739,"pointY":150.90090942382812},"width":1045,"sublayerTransform":[1,0,0,0,0,1,0,0,0,0,1,0,0,0,0,1],"contentsRect":{"y":0,"x":0,"width":1,"height":1},"opacity":1,"edgeAntialiasingMask":0,"height":303,"hidden":true,"anchorPoint":{"pointX":0.5,"pointY":0.5}},"texture":"EFC639BC6D2B9DA8890427392A014891"}]}]},"effects":[],"duration":0.5,"type":"buildIn","attributes":{"direction":13},"name":"apple:wipe","objectID":"15131158-FFE4-47F7-8329-D4736EE47073"}],"automaticPlay":false,"hyperlinks":[],"accessibility":[{"text":"4","targetRectangle":{"y":261.71868896484375,"x":418.4985179901123,"width":16.6845703125,"height":36}},{"text":"3","targetRectangle":{"y":261.71868896484375,"x":567.15626335144043,"width":16.6845703125,"height":36}},{"text":"4","targetRectangle":{"y":261.71868885343139,"x":848.74531364440918,"width":16.6845703125,"height":36}},{"text":"Clases","targetRectangle":{"y":620.72070384025574,"x":5.3019928932189941,"width":79.456000000000003,"height":31}},{"text":"pasted-image.pdf","targetRectangle":{"y":528.1990966796875,"x":868.9886372089386,"width":23.701805114746094,"height":198.83560180664062}},{"text":"3","targetRectangle":{"y":261.71868896484375,"x":699.3549633026123,"width":16.6845703125,"height":36}},{"text":"2","targetRectangle":{"y":261.71868896484375,"x":107.23579216003418,"width":16.6845703125,"height":36}},{"text":"￼","targetRectangle":{"y":719.260009765625,"x":967.53321838378906,"width":36.7060546875,"height":36.92041015625}},{"text":"Screenshot 2019-01-11 01.07.24.png","targetRectangle":{"y":301.1778450012207,"x":75.729095458984375,"width":868.82037353515625,"height":30.681858062744141}},{"text":"1.5 Distribuciones de frecuencias (ejemplo 1)","targetRectangle":{"y":39.050423622131348,"x":29.337646484375,"width":965.32470703125,"height":54}},{"text":"1.2 Descripción de datos: frecuencia de clase","targetRectangle":{"y":93.050423622131348,"x":25.54736328125,"width":972.9052734375,"height":54}},{"text":"4","targetRectangle":{"y":261.71868896484375,"x":241.96590995788574,"width":16.6845703125,"height":36}},{"text":"Frecuencia ","targetRectangle":{"y":605.22070372104645,"x":892.4260086193085,"width":136.83799999999997,"height":31}},{"text":"absoluta","targetRectangle":{"y":636.22070372104645,"x":907.37600861930844,"width":99.710000000000036,"height":31}},{"text":"La frecuencia absoluta o fa es el numero de veces que un valor se repite dentro del conjunto de datos.","targetRectangle":{"y":363.79514956474304,"x":42.095867156982422,"width":948.14822753906208,"height":72.000457763671875}},{"text":"pasted-image.pdf","targetRectangle":{"y":530.04998779296875,"x":91.696133852005005,"width":23.701805114746094,"height":195.13386535644531}},{"text":"La variable de estudio es el número de refrescos de cola que un joven bebe al día. Por lo tanto, los posibles valores de esta variable son:","targetRectangle":{"y":179.26431155204773,"x":42.095867156982422,"width":948.14822753906208,"height":72.000457763671875}}],"baseLayer":{"animations":[],"initialState":{"affineTransform":[1,0,0,1,0,0],"masksToBounds":false,"rotation":0,"scale":1,"position":{"pointX":512,"pointY":384},"width":1024,"sublayerTransform":[1,0,0,0,0,1,0,0,0,0,1,0,0,0,0,1],"contentsRect":{"y":0,"x":0,"width":1,"height":1},"opacity":1,"edgeAntialiasingMask":251658240,"height":768,"hidden":false,"anchorPoint":{"pointX":0.5,"pointY":0.5}},"layers":[{"animations":[],"initialState":{"affineTransform":[1,0,0,1,0,0],"masksToBounds":false,"rotation":0,"scale":1,"position":{"pointX":512,"pointY":384},"width":1024,"sublayerTransform":[1,0,0,0,0,1,0,0,0,0,1,0,0,0,0,1],"contentsRect":{"y":0,"x":0,"width":1,"height":1},"opacity":1,"edgeAntialiasingMask":251658240,"height":768,"hidden":false,"anchorPoint":{"pointX":0.5,"pointY":0.5}},"layers":[{"animations":[],"initialState":{"affineTransform":[1,0,0,1,0,0],"masksToBounds":false,"rotation":0,"scale":1,"position":{"pointX":512,"pointY":384},"width":1024,"sublayerTransform":[1,0,0,0,0,1,0,0,0,0,1,0,0,0,0,1],"contentsRect":{"y":0,"x":0,"width":1,"height":1},"opacity":1,"edgeAntialiasingMask":251658240,"height":768,"hidden":false,"anchorPoint":{"pointX":0.5,"pointY":0.5}},"layers":[{"animations":[],"layers":[],"texturedRectangle":{"isBackgroundTexture":true,"singleTextureOpacity":1,"textureType":1,"textBaseline":0,"textXHeight":0,"isVerticalText":false},"initialState":{"affineTransform":[1,0,0,1,0,0],"masksToBounds":false,"rotation":0,"scale":1,"position":{"pointX":512,"pointY":384},"width":1024,"sublayerTransform":[1,0,0,0,0,1,0,0,0,0,1,0,0,0,0,1],"contentsRect":{"y":0,"x":0,"width":1,"height":1},"opacity":1,"edgeAntialiasingMask":0,"height":768,"hidden":false,"anchorPoint":{"pointX":0.5,"pointY":0.5}},"texture":"9251636AE7EC24F2536617C9E7909BA3"}]}]},{"animations":[],"initialState":{"affineTransform":[1,0,0,1,0,0],"masksToBounds":false,"rotation":0,"scale":1,"position":{"pointX":512,"pointY":384},"width":1024,"sublayerTransform":[1,0,0,0,0,1,0,0,0,0,1,0,0,0,0,1],"contentsRect":{"y":0,"x":0,"width":1,"height":1},"opacity":1,"edgeAntialiasingMask":251658240,"height":768,"hidden":false,"anchorPoint":{"pointX":0.5,"pointY":0.5}},"layers":[{"animations":[],"initialState":{"affineTransform":[1,0,0,1,0,0],"masksToBounds":false,"rotation":0,"scale":1,"position":{"pointX":507.46453857421875,"pointY":58.550423622131348},"width":972,"sublayerTransform":[1,0,0,0,0,1,0,0,0,0,1,0,0,0,0,1],"contentsRect":{"y":0,"x":0,"width":1,"height":1},"opacity":1,"edgeAntialiasingMask":251658240,"height":101,"hidden":false,"anchorPoint":{"pointX":0.5,"pointY":0.5}},"layers":[{"animations":[],"layers":[],"texturedRectangle":{"singleTextureOpacity":1,"textXHeight":0.23713064665841585,"textBaseline":0.87823071810278563,"isBackgroundTexture":true,"isVerticalText":false,"textColor":[0.016150906682014465,0.20410424470901489,1,1],"textureType":6},"initialState":{"affineTransform":[1,0,0,1,0,0],"masksToBounds":false,"rotation":0,"scale":1,"position":{"pointX":491.53546142578125,"pointY":90.449576377868652},"width":972,"sublayerTransform":[1,0,0,0,0,1,0,0,0,0,1,0,0,0,0,1],"contentsRect":{"y":0,"x":0,"width":1,"height":1},"opacity":1,"edgeAntialiasingMask":0,"height":101,"hidden":false,"anchorPoint":{"pointX":0.5,"pointY":0.5}},"texture":"ED29C62767A41465D6783C5C27326D53"}]}]},{"animations":[],"initialState":{"affineTransform":[1,0,0,1,0,0],"masksToBounds":false,"rotation":0,"scale":1,"position":{"pointX":512,"pointY":384},"width":1024,"sublayerTransform":[1,0,0,0,0,1,0,0,0,0,1,0,0,0,0,1],"contentsRect":{"y":0,"x":0,"width":1,"height":1},"opacity":1,"edgeAntialiasingMask":251658240,"height":768,"hidden":false,"anchorPoint":{"pointX":0.5,"pointY":0.5}},"layers":[{"animations":[],"initialState":{"affineTransform":[1,0,0,1,0,0],"masksToBounds":false,"rotation":0,"scale":1,"position":{"pointX":987.28802490234375,"pointY":739.260009765625},"width":84,"sublayerTransform":[1,0,0,0,0,1,0,0,0,0,1,0,0,0,0,1],"contentsRect":{"y":0,"x":0,"width":1,"height":1},"opacity":1,"edgeAntialiasingMask":251658240,"height":58,"hidden":false,"anchorPoint":{"pointX":0.5,"pointY":0.5}},"layers":[{"animations":[],"layers":[],"texturedRectangle":{"singleTextureOpacity":1,"textXHeight":0,"shapePath":{"lineWidth":1,"flatness":0.59999999999999998,"lineCapStyle":0,"elements":[{"type":"MoveToPoint","points":[[3.78802490234375,3.760009765625]]},{"type":"AddLine","points":[[79.984468936920166,3.760009765625]]},{"type":"AddLine","points":[[79.984468936920166,53.680419683456421]]},{"type":"AddLine","points":[[3.78802490234375,53.680419683456421]]},{"type":"CloseSubpath"},{"type":"MoveToPoint","points":[[3.78802490234375,3.760009765625]]}],"windingRule":0,"lineJoinStyle":0,"miterLimit":10},"isBackgroundTexture":true,"textBaseline":0,"isVerticalText":false,"textureType":5},"initialState":{"affineTransform":[1,0,0,1,0,0],"masksToBounds":false,"rotation":0,"scale":1,"position":{"pointX":40.71197509765625,"pointY":27.739990234375},"width":84,"sublayerTransform":[1,0,0,0,0,1,0,0,0,0,1,0,0,0,0,1],"contentsRect":{"y":0,"x":0,"width":1,"height":1},"opacity":1,"edgeAntialiasingMask":0,"height":58,"hidden":false,"anchorPoint":{"pointX":0.5,"pointY":0.5}},"texture":"D2CF0D74CEA9355D4191ED6ED1D34A11"}]}]},{"animations":[],"initialState":{"affineTransform":[1,0,0,1,0,0],"masksToBounds":false,"rotation":0,"scale":1,"position":{"pointX":512,"pointY":384},"width":1024,"sublayerTransform":[1,0,0,0,0,1,0,0,0,0,1,0,0,0,0,1],"contentsRect":{"y":0,"x":0,"width":1,"height":1},"opacity":1,"edgeAntialiasingMask":251658240,"height":768,"hidden":false,"anchorPoint":{"pointX":0.5,"pointY":0.5}},"layers":[{"animations":[],"initialState":{"affineTransform":[1,0,0,1,0,0],"masksToBounds":false,"rotation":0,"scale":1,"position":{"pointX":508.59586715698242,"pointY":209.26431155204773},"width":941,"sublayerTransform":[1,0,0,0,0,1,0,0,0,0,1,0,0,0,0,1],"contentsRect":{"y":0,"x":0,"width":1,"height":1},"opacity":1,"edgeAntialiasingMask":251658240,"height":68,"hidden":false,"anchorPoint":{"pointX":0.5,"pointY":0.5}},"layers":[{"animations":[],"layers":[],"texturedRectangle":{"singleTextureOpacity":1,"textXHeight":0.23117647058823529,"textBaseline":0.8730131983757019,"isBackgroundTexture":true,"isVerticalText":false,"textColor":[0,0,0,1],"textureType":6},"initialState":{"affineTransform":[1,0,0,1,0,0],"masksToBounds":false,"rotation":0,"scale":1,"position":{"pointX":475.40413284301758,"pointY":43.735688447952271},"width":941,"sublayerTransform":[1,0,0,0,0,1,0,0,0,0,1,0,0,0,0,1],"contentsRect":{"y":0,"x":0,"width":1,"height":1},"opacity":1,"edgeAntialiasingMask":0,"height":68,"hidden":false,"anchorPoint":{"pointX":0.5,"pointY":0.5}},"texture":"FA4EA8C2B2453A2ABD2741C8C944964C"}]}]},{"animations":[],"initialState":{"affineTransform":[1,0,0,1,0,0],"masksToBounds":false,"rotation":0,"scale":1,"position":{"pointX":512,"pointY":384},"width":1024,"sublayerTransform":[1,0,0,0,0,1,0,0,0,0,1,0,0,0,0,1],"contentsRect":{"y":0,"x":0,"width":1,"height":1},"opacity":1,"edgeAntialiasingMask":251658240,"height":768,"hidden":false,"anchorPoint":{"pointX":0.5,"pointY":0.5}},"layers":[{"animations":[],"initialState":{"affineTransform":[1,0,0,1,0,0],"masksToBounds":false,"rotation":0,"scale":1,"position":{"pointX":515.22909545898438,"pointY":301.71868896484375},"width":879,"sublayerTransform":[1,0,0,0,0,1,0,0,0,0,1,0,0,0,0,1],"contentsRect":{"y":0,"x":0,"width":1,"height":1},"opacity":1,"edgeAntialiasingMask":251658240,"height":88,"hidden":false,"anchorPoint":{"pointX":0.5,"pointY":0.5}},"layers":[{"animations":[],"layers":[],"texturedRectangle":{"isBackgroundTexture":true,"singleTextureOpacity":1,"textureType":5,"textBaseline":0,"textXHeight":0,"isVerticalText":false},"initialState":{"affineTransform":[1,0,0,1,0,0],"masksToBounds":false,"rotation":0,"scale":1,"position":{"pointX":436.77090454101562,"pointY":40.28131103515625},"width":879,"sublayerTransform":[1,0,0,0,0,1,0,0,0,0,1,0,0,0,0,1],"contentsRect":{"y":0,"x":0,"width":1,"height":1},"opacity":1,"edgeAntialiasingMask":0,"height":88,"hidden":false,"anchorPoint":{"pointX":0.5,"pointY":0.5}},"texture":"4EDDA9365989C60F31824B3B04839638"}]}]},{"animations":[],"initialState":{"affineTransform":[1,0,0,1,0,0],"masksToBounds":false,"rotation":0,"scale":1,"position":{"pointX":512,"pointY":384},"width":1024,"sublayerTransform":[1,0,0,0,0,1,0,0,0,0,1,0,0,0,0,1],"contentsRect":{"y":0,"x":0,"width":1,"height":1},"opacity":1,"edgeAntialiasingMask":251658240,"height":768,"hidden":false,"anchorPoint":{"pointX":0.5,"pointY":0.5}},"layers":[{"animations":[],"initialState":{"affineTransform":[1,0,0,1,0,0],"masksToBounds":false,"rotation":0,"scale":1,"position":{"pointX":523.3019917011261,"pointY":608.09909057617188},"width":1045,"sublayerTransform":[1,0,0,0,0,1,0,0,0,0,1,0,0,0,0,1],"contentsRect":{"y":0,"x":0,"width":1,"height":1},"opacity":1,"edgeAntialiasingMask":251658240,"height":303,"hidden":false,"anchorPoint":{"pointX":0.5,"pointY":0.5}},"objectID":"15131158-FFE4-47F7-8329-D4736EE47073","layers":[{"animations":[],"layers":[],"texturedRectangle":{"isBackgroundTexture":true,"singleTextureOpacity":1,"textureType":5,"textBaseline":0,"textXHeight":0,"isVerticalText":false},"initialState":{"affineTransform":[1,0,0,1,0,0],"masksToBounds":false,"rotation":0,"scale":1,"position":{"pointX":519.6980082988739,"pointY":150.90090942382812},"width":1045,"sublayerTransform":[1,0,0,0,0,1,0,0,0,0,1,0,0,0,0,1],"contentsRect":{"y":0,"x":0,"width":1,"height":1},"opacity":1,"edgeAntialiasingMask":0,"height":303,"hidden":true,"anchorPoint":{"pointX":0.5,"pointY":0.5}},"texture":"EFC639BC6D2B9DA8890427392A014891"}]}]},{"animations":[],"initialState":{"affineTransform":[1,0,0,1,0,0],"masksToBounds":false,"rotation":0,"scale":1,"position":{"pointX":512,"pointY":384},"width":1024,"sublayerTransform":[1,0,0,0,0,1,0,0,0,0,1,0,0,0,0,1],"contentsRect":{"y":0,"x":0,"width":1,"height":1},"opacity":1,"edgeAntialiasingMask":251658240,"height":768,"hidden":false,"anchorPoint":{"pointX":0.5,"pointY":0.5}},"layers":[{"animations":[],"initialState":{"affineTransform":[1,0,0,1,0,0],"masksToBounds":false,"rotation":0,"scale":1,"position":{"pointX":508.59586715698242,"pointY":393.79514956474304},"width":941,"sublayerTransform":[1,0,0,0,0,1,0,0,0,0,1,0,0,0,0,1],"contentsRect":{"y":0,"x":0,"width":1,"height":1},"opacity":1,"edgeAntialiasingMask":251658240,"height":68,"hidden":false,"anchorPoint":{"pointX":0.5,"pointY":0.5}},"objectID":"87B8599C-80D5-4128-A775-69BBD845A03A","layers":[{"animations":[],"layers":[],"texturedRectangle":{"singleTextureOpacity":1,"textXHeight":0.23117647058823529,"textBaseline":0.88081963973886823,"isBackgroundTexture":true,"isVerticalText":false,"textColor":[0,0,0,1],"textureType":6},"initialState":{"affineTransform":[1,0,0,1,0,0],"masksToBounds":false,"rotation":0,"scale":1,"position":{"pointX":475.40413284301758,"pointY":43.204850435256958},"width":941,"sublayerTransform":[1,0,0,0,0,1,0,0,0,0,1,0,0,0,0,1],"contentsRect":{"y":0,"x":0,"width":1,"height":1},"opacity":1,"edgeAntialiasingMask":0,"height":68,"hidden":false,"anchorPoint":{"pointX":0.5,"pointY":0.5}},"texture":"031D85F0AC0685B6A950E6766B703A20"}]}]}]}},{"effects":[{"beginTime":0,"baseLayer":{"animations":[],"initialState":{"affineTransform":[1,0,0,1,0,0],"masksToBounds":false,"rotation":0,"scale":1,"position":{"pointX":512,"pointY":384},"width":1024,"sublayerTransform":[1,0,0,0,0,1,0,0,0,0,1,0,0,0,0,1],"contentsRect":{"y":0,"x":0,"width":1,"height":1},"opacity":1,"edgeAntialiasingMask":251658240,"height":768,"hidden":false,"anchorPoint":{"pointX":0.5,"pointY":0.5}},"objectID":"0","layers":[{"animations":[],"initialState":{"affineTransform":[1,0,0,1,0,0],"masksToBounds":false,"rotation":0,"scale":1,"position":{"pointX":512,"pointY":384},"width":1024,"sublayerTransform":[1,0,0,0,0,1,0,0,0,0,1,-0.00049229876906403734,0,0,0,1],"contentsRect":{"y":0,"x":0,"width":1,"height":1},"opacity":1,"edgeAntialiasingMask":251658240,"height":768,"hidden":false,"anchorPoint":{"pointX":0.5,"pointY":0.5}},"layers":[{"animations":[],"layers":[],"texturedRectangle":{"isBackgroundTexture":false,"singleTextureOpacity":1,"textureType":0,"textBaseline":0,"textXHeight":0,"isVerticalText":false},"initialState":{"affineTransform":[1,0,0,1,0,0],"masksToBounds":false,"rotation":0,"scale":1,"position":{"pointX":512,"pointY":384},"width":1024,"sublayerTransform":[1,0,0,0,0,1,0,0,0,0,1,0,0,0,0,1],"contentsRect":{"y":0,"x":0,"width":1,"height":1},"opacity":1,"edgeAntialiasingMask":0,"height":768,"hidden":false,"anchorPoint":{"pointX":0.5,"pointY":0.5}},"texture":"4C59AFC708246E52175AA6414ACEAEF1"},{"animations":[{"repeatCount":0,"removedOnCompletion":false,"from":{"scalar":1},"timingFunction":"EaseInEaseOut","additive":false,"timeOffset":0,"autoreverses":false,"property":"opacity","fillMode":"both","duration":1,"beginTime":0,"to":{"scalar":0}}],"layers":[],"texturedRectangle":{"isBackgroundTexture":false,"singleTextureOpacity":1,"textureType":0,"textBaseline":0,"textXHeight":0,"isVerticalText":false},"initialState":{"affineTransform":[1,0,0,1,0,0],"masksToBounds":false,"rotation":0,"scale":1,"position":{"pointX":512,"pointY":384},"width":1024,"sublayerTransform":[1,0,0,0,0,1,0,0,0,0,1,0,0,0,0,1],"contentsRect":{"y":0,"x":0,"width":1,"height":1},"opacity":1,"edgeAntialiasingMask":0,"height":768,"hidden":false,"anchorPoint":{"pointX":0.5,"pointY":0.5}},"texture":"80E549313E6B8EF3E7F6E6F923B49386"}]}]},"effects":[],"duration":1,"type":"transition","attributes":{"direction":13},"name":"com.apple.iWork.Keynote.BUKFlop","objectID":"0"}],"automaticPlay":false,"hyperlinks":[],"accessibility":[{"text":"4","targetRectangle":{"y":261.71868896484375,"x":418.4985179901123,"width":16.6845703125,"height":36}},{"text":"3","targetRectangle":{"y":261.71868896484375,"x":567.15626335144043,"width":16.6845703125,"height":36}},{"text":"4","targetRectangle":{"y":261.71868885343139,"x":848.74531364440918,"width":16.6845703125,"height":36}},{"text":"Clases","targetRectangle":{"y":620.72070384025574,"x":5.3019928932189941,"width":79.456000000000003,"height":31}},{"text":"pasted-image.pdf","targetRectangle":{"y":528.1990966796875,"x":868.9886372089386,"width":23.701805114746094,"height":198.83560180664062}},{"text":"3","targetRectangle":{"y":261.71868896484375,"x":699.3549633026123,"width":16.6845703125,"height":36}},{"text":"2","targetRectangle":{"y":261.71868896484375,"x":107.23579216003418,"width":16.6845703125,"height":36}},{"text":"￼","targetRectangle":{"y":719.260009765625,"x":967.53321838378906,"width":36.7060546875,"height":36.92041015625}},{"text":"Screenshot 2019-01-11 01.07.24.png","targetRectangle":{"y":301.1778450012207,"x":75.729095458984375,"width":868.82037353515625,"height":30.681858062744141}},{"text":"1.5 Distribuciones de frecuencias (ejemplo 1)","targetRectangle":{"y":39.050423622131348,"x":29.337646484375,"width":965.32470703125,"height":54}},{"text":"1.2 Descripción de datos: frecuencia de clase","targetRectangle":{"y":93.050423622131348,"x":25.54736328125,"width":972.9052734375,"height":54}},{"text":"4","targetRectangle":{"y":261.71868896484375,"x":241.96590995788574,"width":16.6845703125,"height":36}},{"text":"Frecuencia ","targetRectangle":{"y":605.22070372104645,"x":892.4260086193085,"width":136.83799999999997,"height":31}},{"text":"absoluta","targetRectangle":{"y":636.22070372104645,"x":907.37600861930844,"width":99.710000000000036,"height":31}},{"text":"La frecuencia absoluta o fa es el numero de veces que un valor se repite dentro del conjunto de datos.","targetRectangle":{"y":363.79514956474304,"x":42.095867156982422,"width":948.14822753906208,"height":72.000457763671875}},{"text":"pasted-image.pdf","targetRectangle":{"y":530.04998779296875,"x":91.696133852005005,"width":23.701805114746094,"height":195.13386535644531}},{"text":"La variable de estudio es el número de refrescos de cola que un joven bebe al día. Por lo tanto, los posibles valores de esta variable son:","targetRectangle":{"y":179.26431155204773,"x":42.095867156982422,"width":948.14822753906208,"height":72.000457763671875}}],"baseLayer":{"animations":[],"initialState":{"affineTransform":[1,0,0,1,0,0],"masksToBounds":false,"rotation":0,"scale":1,"position":{"pointX":512,"pointY":384},"width":1024,"sublayerTransform":[1,0,0,0,0,1,0,0,0,0,1,0,0,0,0,1],"contentsRect":{"y":0,"x":0,"width":1,"height":1},"opacity":1,"edgeAntialiasingMask":251658240,"height":768,"hidden":false,"anchorPoint":{"pointX":0.5,"pointY":0.5}},"objectID":"0","layers":[{"animations":[],"initialState":{"affineTransform":[1,0,0,1,0,0],"masksToBounds":false,"rotation":0,"scale":1,"position":{"pointX":512,"pointY":384},"width":1024,"sublayerTransform":[1,0,0,0,0,1,0,0,0,0,1,-0.00049229876906403734,0,0,0,1],"contentsRect":{"y":0,"x":0,"width":1,"height":1},"opacity":1,"edgeAntialiasingMask":251658240,"height":768,"hidden":false,"anchorPoint":{"pointX":0.5,"pointY":0.5}},"layers":[{"animations":[],"layers":[],"texturedRectangle":{"isBackgroundTexture":false,"singleTextureOpacity":1,"textureType":0,"textBaseline":0,"textXHeight":0,"isVerticalText":false},"initialState":{"affineTransform":[1,0,0,1,0,0],"masksToBounds":false,"rotation":0,"scale":1,"position":{"pointX":512,"pointY":384},"width":1024,"sublayerTransform":[1,0,0,0,0,1,0,0,0,0,1,0,0,0,0,1],"contentsRect":{"y":0,"x":0,"width":1,"height":1},"opacity":1,"edgeAntialiasingMask":0,"height":768,"hidden":false,"anchorPoint":{"pointX":0.5,"pointY":0.5}},"texture":"80E549313E6B8EF3E7F6E6F923B49386"}]}]}}]}