{"assets":{"922F44C47E0F21840898C2117F93D847":{"type":"texture","index":1,"url":{"native":"assets\/25679E24-05DA-4427-ADE6-0ED86BC0674E.pdf"},"width":1024,"height":768},"1E9B4E206C2BD609B7C34E27C2A3BA61":{"type":"texture","index":0,"url":{"native":"assets\/25679E24-05DA-4427-ADE6-0ED86BC0674E.pdf"},"width":1024,"height":768}},"events":[{"effects":[{"beginTime":0,"baseLayer":{"animations":[],"initialState":{"affineTransform":[1,0,0,1,0,0],"masksToBounds":false,"rotation":0,"scale":1,"position":{"pointX":512,"pointY":384},"width":1024,"sublayerTransform":[1,0,0,0,0,1,0,0,0,0,1,0,0,0,0,1],"contentsRect":{"y":0,"x":0,"width":1,"height":1},"opacity":1,"edgeAntialiasingMask":251658240,"height":768,"hidden":false,"anchorPoint":{"pointX":0.5,"pointY":0.5}},"objectID":"0","layers":[{"animations":[],"initialState":{"affineTransform":[1,0,0,1,0,0],"masksToBounds":false,"rotation":0,"scale":1,"position":{"pointX":512,"pointY":384},"width":1024,"sublayerTransform":[1,0,0,0,0,1,0,0,0,0,1,-0.00049229876906403734,0,0,0,1],"contentsRect":{"y":0,"x":0,"width":1,"height":1},"opacity":1,"edgeAntialiasingMask":251658240,"height":768,"hidden":false,"anchorPoint":{"pointX":0.5,"pointY":0.5}},"layers":[{"animations":[],"layers":[],"texturedRectangle":{"isBackgroundTexture":false,"singleTextureOpacity":1,"textureType":0,"textBaseline":0,"textXHeight":0,"isVerticalText":false},"initialState":{"affineTransform":[1,0,0,1,0,0],"masksToBounds":false,"rotation":0,"scale":1,"position":{"pointX":512,"pointY":384},"width":1024,"sublayerTransform":[1,0,0,0,0,1,0,0,0,0,1,0,0,0,0,1],"contentsRect":{"y":0,"x":0,"width":1,"height":1},"opacity":1,"edgeAntialiasingMask":0,"height":768,"hidden":false,"anchorPoint":{"pointX":0.5,"pointY":0.5}},"texture":"922F44C47E0F21840898C2117F93D847"},{"animations":[{"repeatCount":0,"removedOnCompletion":false,"from":{"scalar":1},"timingFunction":"EaseInEaseOut","additive":false,"timeOffset":0,"autoreverses":false,"property":"opacity","fillMode":"both","duration":1,"beginTime":0,"to":{"scalar":0}}],"layers":[],"texturedRectangle":{"isBackgroundTexture":false,"singleTextureOpacity":1,"textureType":0,"textBaseline":0,"textXHeight":0,"isVerticalText":false},"initialState":{"affineTransform":[1,0,0,1,0,0],"masksToBounds":false,"rotation":0,"scale":1,"position":{"pointX":512,"pointY":384},"width":1024,"sublayerTransform":[1,0,0,0,0,1,0,0,0,0,1,0,0,0,0,1],"contentsRect":{"y":0,"x":0,"width":1,"height":1},"opacity":1,"edgeAntialiasingMask":0,"height":768,"hidden":false,"anchorPoint":{"pointX":0.5,"pointY":0.5}},"texture":"1E9B4E206C2BD609B7C34E27C2A3BA61"}]}]},"effects":[],"duration":1,"type":"transition","attributes":{"direction":13},"name":"com.apple.iWork.Keynote.BUKFlop","objectID":"0"}],"automaticPlay":false,"hyperlinks":[],"accessibility":[{"text":"La teoría de la decisión estadística es una herramienta básica para la toma de decisiones basada en evidencia científica. Consiste en plantear las hipótesis posibles y luego aplicarles un test estadístico (docimasia estadística). ","targetRectangle":{"y":480.70663452148438,"x":61.391209910180805,"width":916.06937785837351,"height":160}},{"text":"1.1 Conceptos básicos de estadística: teoría de decisión","targetRectangle":{"y":48,"x":78.264556884765625,"width":856.962890625,"height":144}},{"text":"Teoría de la decisión estadística - Probabilidad y estadística - Apuntes - Capítulo12 - Parte1, Apuntes de Probabilidad. Universidad Politécnica de Cartagena.","targetRectangle":{"y":275.50289964675903,"x":314.91342186927795,"width":652.38672740745562,"height":93}},{"text":"￼","targetRectangle":{"y":719.260009765625,"x":976.70973205566406,"width":18.35302734375,"height":36.92041015625}},{"text":"docsity.png","targetRectangle":{"y":289.11782836914062,"x":40.812541961669922,"width":238.55607604980469,"height":65.770133972167969}},{"text":"Screenshot 2018-01-08 22.19.06.png","targetRectangle":{"y":389.62789916992188,"x":180,"width":664,"height":76}}],"baseLayer":{"animations":[],"initialState":{"affineTransform":[1,0,0,1,0,0],"masksToBounds":false,"rotation":0,"scale":1,"position":{"pointX":512,"pointY":384},"width":1024,"sublayerTransform":[1,0,0,0,0,1,0,0,0,0,1,0,0,0,0,1],"contentsRect":{"y":0,"x":0,"width":1,"height":1},"opacity":1,"edgeAntialiasingMask":251658240,"height":768,"hidden":false,"anchorPoint":{"pointX":0.5,"pointY":0.5}},"objectID":"0","layers":[{"animations":[],"initialState":{"affineTransform":[1,0,0,1,0,0],"masksToBounds":false,"rotation":0,"scale":1,"position":{"pointX":512,"pointY":384},"width":1024,"sublayerTransform":[1,0,0,0,0,1,0,0,0,0,1,-0.00049229876906403734,0,0,0,1],"contentsRect":{"y":0,"x":0,"width":1,"height":1},"opacity":1,"edgeAntialiasingMask":251658240,"height":768,"hidden":false,"anchorPoint":{"pointX":0.5,"pointY":0.5}},"layers":[{"animations":[],"layers":[],"texturedRectangle":{"isBackgroundTexture":false,"singleTextureOpacity":1,"textureType":0,"textBaseline":0,"textXHeight":0,"isVerticalText":false},"initialState":{"affineTransform":[1,0,0,1,0,0],"masksToBounds":false,"rotation":0,"scale":1,"position":{"pointX":512,"pointY":384},"width":1024,"sublayerTransform":[1,0,0,0,0,1,0,0,0,0,1,0,0,0,0,1],"contentsRect":{"y":0,"x":0,"width":1,"height":1},"opacity":1,"edgeAntialiasingMask":0,"height":768,"hidden":false,"anchorPoint":{"pointX":0.5,"pointY":0.5}},"texture":"1E9B4E206C2BD609B7C34E27C2A3BA61"}]}]}}]}